normalizer/__init__.py
normalizer/const.py
normalizer/normalize.py
csebuetnlp_normalizer-1.0.0.dist-info/METADATA
csebuetnlp_normalizer-1.0.0.dist-info/WHEEL
csebuetnlp_normalizer-1.0.0.dist-info/top_level.txt
csebuetnlp_normalizer-1.0.0.dist-info/RECORD
