Metadata-Version: 2.1
Name: csebuetnlp-normalizer
Version: 1.0.0
Summary: Normalizer for bengali / english text.
Author-email: Sawradip Saha <sawradip0@gmail.com>
Classifier: Programming Language :: Python :: 3
Classifier: License :: OSI Approved :: MIT License
Classifier: Operating System :: OS Independent
Requires-Python: >=3.5
Requires-Dist: regex
Requires-Dist: emoji ==1.4.2
Requires-Dist: ftfy ==6.0.3
